tensorial/__init__.py
tensorial/_provides.py
tensorial/_utils.py
tensorial/base.py
tensorial/config.py
tensorial/nn.py
tensorial/nn_utils.py
tensorial/tensors.py
tensorial/typing.py
tensorial/utils.py
tensorial/datasets/__init__.py
tensorial/datasets/qm9.py
tensorial/gcnn/__init__.py
tensorial/gcnn/_base.py
tensorial/gcnn/_common.py
tensorial/gcnn/_diff.py
tensorial/gcnn/_edgewise.py
tensorial/gcnn/_experimental.py
tensorial/gcnn/_mace.py
tensorial/gcnn/_message_passing.py
tensorial/gcnn/_modules.py
tensorial/gcnn/_nequip.py
tensorial/gcnn/_nodewise.py
tensorial/gcnn/_spatial.py
tensorial/gcnn/_tree.py
tensorial/gcnn/calc.py
tensorial/gcnn/derivatives.py
tensorial/gcnn/graph_ops.py
tensorial/gcnn/keys.py
tensorial/gcnn/losses.py
tensorial/gcnn/metrics.py
tensorial/gcnn/random.py
tensorial/gcnn/typing.py
tensorial/gcnn/utils.py
tensorial/gcnn/atomic/__init__.py
tensorial/gcnn/atomic/_importing.py
tensorial/gcnn/atomic/_metrics.py
tensorial/gcnn/atomic/_modules.py
tensorial/gcnn/atomic/keys.py
tensorial/gcnn/data/__init__.py
tensorial/gcnn/data/_batching.py
tensorial/gcnn/data/_common.py
tensorial/gcnn/data/_dataloader.py
tensorial/gcnn/data/_datamodule.py
tensorial/gcnn/experimental/__init__.py
tensorial/gcnn/experimental/derivatives.py
tensorial/gcnn/experimental/utils.py
tensorial/geometry/__init__.py
tensorial/geometry/distances.py
tensorial/geometry/jax_neighbours.py
tensorial/geometry/np_neighbours.py
tensorial/geometry/unit_cells.py
tensorial/metrics/__init__.py
tensorial/metrics/collections.py
tensorial/metrics/evaluator.py
tensorial/metrics/metric.py
tensorial/reaxkit/__init__.py
tensorial/reaxkit/_metrics_printer.py
tensorial/reaxkit/_module.py
tensorial/reaxkit/cli.py
tensorial/reaxkit/config.py
tensorial/reaxkit/evaluate.py
tensorial/reaxkit/from_data.py
tensorial/reaxkit/keys.py
tensorial/reaxkit/train.py
tensorial/reaxkit/listeners/__init__.py
tensorial/reaxkit/listeners/parity_plotter.py
tensorial/reaxkit/utils/__init__.py
tensorial-0.6.0.dist-info/entry_points.txt
tensorial-0.6.0.dist-info/licenses/LICENSE.txt
tensorial-0.6.0.dist-info/WHEEL
tensorial-0.6.0.dist-info/METADATA
tensorial-0.6.0.dist-info/RECORD
